failwatch/__init__.py
failwatch/client.py
failwatch/exceptions.py
failwatch-0.1.0.dist-info/METADATA
failwatch-0.1.0.dist-info/WHEEL
failwatch-0.1.0.dist-info/RECORD
