Metadata-Version: 2.4
Name: failwatch
Version: 0.1.0
Summary: The Missing Safety Layer for AI Agents
Project-URL: Homepage, https://github.com/Ludwig1827/FailWatch
Project-URL: Bug Tracker, https://github.com/Ludwig1827/FailWatch/issues
Author-email: Your Name <your.email@example.com>
License-Expression: MIT
Classifier: License :: OSI Approved :: MIT License
Classifier: Operating System :: OS Independent
Classifier: Programming Language :: Python :: 3
Classifier: Topic :: Scientific/Engineering :: Artificial Intelligence
Classifier: Topic :: Security
Requires-Python: >=3.8
Requires-Dist: fastapi
Requires-Dist: pydantic
Requires-Dist: python-dotenv
Requires-Dist: requests
